django_classy_views/__init__.py
django_classy_views-0.0.2.dist-info/METADATA
django_classy_views-0.0.2.dist-info/WHEEL
django_classy_views-0.0.2.dist-info/top_level.txt
django_classy_views-0.0.2.dist-info/RECORD
