Metadata-Version: 2.4
Name: django-classy-views
Version: 0.0.2
Summary: An academic experiment package
Home-page: https://pypi.org/project/django-classy-views/
Author: Guangye Bai
Author-email: 2253637@tongji.edu.cn
License: MIT
Keywords: django,django-classy-views,django-views,experiment,supply chain,security
Classifier: Development Status :: 2 - Pre-Alpha
Classifier: Intended Audience :: Developers
Classifier: License :: OSI Approved :: MIT License
Classifier: Programming Language :: Python :: 3
Classifier: Topic :: Software Development :: Libraries
Classifier: Topic :: Database :: Front-Ends
Requires-Python: >=3.6
Dynamic: author
Dynamic: author-email
Dynamic: classifier
Dynamic: description
Dynamic: description-content-type
Dynamic: home-page
Dynamic: keywords
Dynamic: license
Dynamic: requires-python
Dynamic: summary
